{
  "_default": {
    "1": {
      "fname": "Sarah",
      "lname": "Johnson",
      "DBirth": "01/06/2001",
      "gender": "female",
      "rang": "1"
    },
    "2": {
      "fname": "Smith",
      "lname": "nathan",
      "DBirth": "2000",
      "gender": "male",
      "rang": "2"
    },
    "3": {
      "fname": "John",
      "lname": "Smithas",
      "DBirth": "01/02/2000",
      "gender": "male",
      "rang": "3"
    },
    "4": {
      "fname": "Sean",
      "lname": "Spinoza",
      "DBirth": "01/02/2000",
      "gender": "male",
      "rang": "4"
    },
    "5": {
      "fname": "Teddy",
      "lname": "Bear",
      "DBirth": "01/02/2001",
      "gender": "male",
      "rang": "5"
    },
    "6": {
      "fname": "Rosa",
      "lname": "france",
      "DBirth": "1979",
      "gender": "female",
      "rang": "6"
    },
    "7": {
      "fname": "Paul",
      "lname": "Lapin",
      "DBirth": "1998",
      "gender": "male",
      "rang": "7"
    },
    "8": {
      "fname": "Zora",
      "lname": "Regis",
      "DBirth": "1999",
      "gender": "female",
      "rang": "8"
    }
  }
}
