{"_default": {"1": {"equipe_B:": [{"fname": "Teddy", "lname": "Bear", "DBirth": "01/02/2001", "gender": "male", "rang": "5"}, {"fname": "Rosa", "lname": "france", "DBirth": "1979", "gender": "female", "rang": "6"}, {"fname": "Paul", "lname": "Lapin", "DBirth": "1998", "gender": "male", "rang": "7"}, {"fname": "Zora", "lname": "Regis", "DBirth": "1999", "gender": "female", "rang": "8"}]}, "2": {"equipe_B:": [{"fname": "Teddy", "lname": "Bear", "DBirth": "01/02/2001", "gender": "male", "rang": "5"}, {"fname": "Rosa", "lname": "france", "DBirth": "1979", "gender": "female", "rang": "6"}, {"fname": "Paul", "lname": "Lapin", "DBirth": "1998", "gender": "male", "rang": "7"}, {"fname": "Zora", "lname": "Regis", "DBirth": "1999", "gender": "female", "rang": "8"}]}, "3": {"Test ": ""}, "4": {"Test ": "1"}, "5": {"Test ": "0.5"}, "6": {"Test ": "1"}}}